discordrpc/__init__.py
discordrpc/baseclient.py
discordrpc/client.py
discordrpc/exceptions.py
discordrpc/payloads.py
discordrpc/presence.py
discordrpc/utils.py
Harvard_Lib-1.0.0.dist-info/LICENSE
Harvard_Lib-1.0.0.dist-info/METADATA
Harvard_Lib-1.0.0.dist-info/WHEEL
Harvard_Lib-1.0.0.dist-info/top_level.txt
Harvard_Lib-1.0.0.dist-info/RECORD
